n_grammer_pytorch/__init__.py
n_grammer_pytorch/n_grammer_pytorch.py
n_grammer_pytorch-0.0.14.dist-info/LICENSE
n_grammer_pytorch-0.0.14.dist-info/METADATA
n_grammer_pytorch-0.0.14.dist-info/WHEEL
n_grammer_pytorch-0.0.14.dist-info/top_level.txt
n_grammer_pytorch-0.0.14.dist-info/RECORD
