Metadata-Version: 2.1
Name: n-grammer-pytorch
Version: 0.0.14
Summary: N-Grammer - Pytorch
Home-page: https://github.com/lucidrains/n-grammer-pytorch
Author: Phil Wang
Author-email: lucidrains@gmail.com
License: MIT
Keywords: artificial intelligence,attention mechanism,transformers,n-grams,memory
Classifier: Development Status :: 4 - Beta
Classifier: Intended Audience :: Developers
Classifier: Topic :: Scientific/Engineering :: Artificial Intelligence
Classifier: License :: OSI Approved :: MIT License
Classifier: Programming Language :: Python :: 3.6
License-File: LICENSE
Requires-Dist: einops (>=0.3)
Requires-Dist: sympy
Requires-Dist: torch (>=1.6)
